ape_cairo/__init__.py
ape_cairo/compiler.py
ape_cairo/py.typed
ape_cairo/version.py
ape_cairo-0.6.1.dist-info/LICENSE
ape_cairo-0.6.1.dist-info/METADATA
ape_cairo-0.6.1.dist-info/WHEEL
ape_cairo-0.6.1.dist-info/top_level.txt
ape_cairo-0.6.1.dist-info/RECORD
