Metadata-Version: 2.1
Name: ape-cairo
Version: 0.6.1
Summary: ape-cairo: A compiler plugin for the cairo programming language
Home-page: https://github.com/ApeWorX/ape-cairo
Author: ApeWorX Ltd.
Author-email: admin@apeworx.io
License: Apache-2.0
Keywords: ethereum
Platform: UNKNOWN
Classifier: Development Status :: 4 - Beta
Classifier: Intended Audience :: Developers
Classifier: License :: OSI Approved :: Apache Software License
Classifier: Natural Language :: English
Classifier: Operating System :: MacOS
Classifier: Operating System :: POSIX
Classifier: Programming Language :: Python :: 3
Classifier: Programming Language :: Python :: 3.8
Classifier: Programming Language :: Python :: 3.9
Requires-Python: >=3.8,<3.11
License-File: LICENSE
Requires-Dist: eth-ape (<0.7,>=0.6.8)
Requires-Dist: ethpm-types
Provides-Extra: dev
Requires-Dist: pytest (<8,>=6.0) ; extra == 'dev'
Requires-Dist: pytest-xdist ; extra == 'dev'
Requires-Dist: pytest-cov ; extra == 'dev'
Requires-Dist: hypothesis (<7.0,>=6.70) ; extra == 'dev'
Requires-Dist: black (>=23.3.0) ; extra == 'dev'
Requires-Dist: mypy (<1,>=0.991) ; extra == 'dev'
Requires-Dist: types-setuptools ; extra == 'dev'
Requires-Dist: flake8 (<7,>=6.0.0) ; extra == 'dev'
Requires-Dist: isort (<6,>=5.10.1) ; extra == 'dev'
Requires-Dist: mdformat (<0.8,>=0.7.16) ; extra == 'dev'
Requires-Dist: mdformat-gfm (<0.4,>=0.3.5) ; extra == 'dev'
Requires-Dist: mdformat-frontmatter (<0.5,>=0.4.1) ; extra == 'dev'
Requires-Dist: setuptools ; extra == 'dev'
Requires-Dist: wheel ; extra == 'dev'
Requires-Dist: twine ; extra == 'dev'
Requires-Dist: commitizen (<3,>=2.42) ; extra == 'dev'
Requires-Dist: pre-commit ; extra == 'dev'
Requires-Dist: pytest-watch ; extra == 'dev'
Requires-Dist: IPython ; extra == 'dev'
Requires-Dist: ipdb ; extra == 'dev'
Provides-Extra: lint
Requires-Dist: black (>=23.3.0) ; extra == 'lint'
Requires-Dist: mypy (<1,>=0.991) ; extra == 'lint'
Requires-Dist: types-setuptools ; extra == 'lint'
Requires-Dist: flake8 (<7,>=6.0.0) ; extra == 'lint'
Requires-Dist: isort (<6,>=5.10.1) ; extra == 'lint'
Requires-Dist: mdformat (<0.8,>=0.7.16) ; extra == 'lint'
Requires-Dist: mdformat-gfm (<0.4,>=0.3.5) ; extra == 'lint'
Requires-Dist: mdformat-frontmatter (<0.5,>=0.4.1) ; extra == 'lint'
Provides-Extra: release
Requires-Dist: setuptools ; extra == 'release'
Requires-Dist: wheel ; extra == 'release'
Requires-Dist: twine ; extra == 'release'
Provides-Extra: test
Requires-Dist: pytest (<8,>=6.0) ; extra == 'test'
Requires-Dist: pytest-xdist ; extra == 'test'
Requires-Dist: pytest-cov ; extra == 'test'
Requires-Dist: hypothesis (<7.0,>=6.70) ; extra == 'test'
